{
  "version": "2.0",
  "columns": 6,
  "tiles": [
    {
      "type": "PING",
      "label": "Сайт chelonco.ru",
      "params": { "hostname": "chelonco.ru" }
    },
    {
      "type": "PORT",
      "label": "Juniper SRX SSH Service",
      "params": { "hostname": "nas.chelonco.ru", "port": 22 }
    },
    {
      "type": "HTTP-STATUS",
      "label": "Служба поддержки HESK",
      "params": {      
      "url": "http://hesk.chelonco.ru/admin/index.php",
      "statusCodeMax": 299 
      }
    }
  ]
}
